MANIFEST.in
setup.cfg
setup.py
django_staggered_selects.egg-info/PKG-INFO
django_staggered_selects.egg-info/SOURCES.txt
django_staggered_selects.egg-info/dependency_links.txt
django_staggered_selects.egg-info/top_level.txt
staggered_selects/__init__.py
staggered_selects/fields.py
staggered_selects/widgets.py
staggered_selects/static/staggered_select/css/staggered.css
staggered_selects/static/staggered_select/js/staggered.js