Metadata-Version: 1.1
Name: django-staggered-selects
Version: 0.1.2
Summary: Staggered drop-down menus for the Django admin
Home-page: https://github.com/datahub/django-staggered-selects
Author: Allan James Vestal
Author-email: datahub@jrn.com
License: MIT License
Download-URL: https://github.com/datahub/django-staggered-selects/tarball/0.1.2
Platform: UNKNOWN
Classifier: Development Status :: 4 - Beta
Classifier: Environment :: Web Environment
Classifier: Framework :: Django
Classifier: Intended Audience :: Developers
Classifier: License :: OSI Approved :: MIT License
Classifier: Operating System :: OS Independent
Classifier: Programming Language :: Python
Classifier: Topic :: Software Development :: Libraries :: Python Modules
